pgadmin_site/__init__.py
pgadmin_site/card_designer.py
pgadmin_site/cli.py
pgadmin_site/main.py
pgadmin_site/zap.py
pgadmin_site/demo/README.md
pgadmin_site/demo/a.py
pgadmin_site/demo/example_site.py
pgadmin_site/demo/import_data.sql
pgadmin_site/demo/product_card.json
pgadmin_site/demo/schema.sql
pgadmin_site/modul/module2.py
pgadmin_site/modul/module3.py
pgadmin_site/modul/module4.py
pgadmin_site/modul/product_app5.py
pgadmin_site/templates/add_column.html
pgadmin_site/templates/add_row.html
pgadmin_site/templates/card_svg.html
pgadmin_site/templates/card_view.html
pgadmin_site/templates/edit_row.html
pgadmin_site/templates/error.html
pgadmin_site/templates/foto_block.html
pgadmin_site/templates/import_table.html
pgadmin_site/templates/index.html
pgadmin_site/templates/structure.html
pgadmin_site/templates/table.html
pgadmin_site-0.10.0.dist-info/licenses/LICENSE
pgadmin_site-0.10.0.dist-info/METADATA
pgadmin_site-0.10.0.dist-info/WHEEL
pgadmin_site-0.10.0.dist-info/entry_points.txt
pgadmin_site-0.10.0.dist-info/top_level.txt
pgadmin_site-0.10.0.dist-info/RECORD
