Metadata-Version: 2.4
Name: pgadmin-site
Version: 0.10.0
Summary: Библиотека для создания локального сайта для работы с таблицами PostgreSQL
Author-email: Your Name <your.email@example.com>
License: MIT
Project-URL: Homepage, https://github.com/yourusername/pgadmin-site
Project-URL: Bug Tracker, https://github.com/yourusername/pgadmin-site/issues
Classifier: Programming Language :: Python :: 3
Classifier: License :: OSI Approved :: MIT License
Classifier: Operating System :: OS Independent
Requires-Python: >=3.8
License-File: LICENSE
Requires-Dist: flask>=2.0.0
Requires-Dist: psycopg2-binary>=2.9.3
Requires-Dist: SQLAlchemy>=2.0.0
Requires-Dist: wtforms>=3.0.0
Requires-Dist: flask-sqlalchemy>=3.0.0
Requires-Dist: click>=8.0.0
Requires-Dist: openai>=1.0.0
Requires-Dist: xlsxwriter>=3.0.0
Requires-Dist: pandas>=2.0.0
Dynamic: license-file
